Lab_09/Ejercicio02/FlipFlopT.v
//Electronica Digital 1
// Marco Duarte
// Ejercicio 02
// FlipFlop tipo T


module FFD(
    input wire clk, reset, En, D,
    output reg Q);

        always @(posedge clk or posedge reset) begin
            if(reset)
                Q <= 0;
            else if (En)
                Q <= D; 
        end
endmodule

module FFT(
    input wire clk, reset, En,
    output wire Q);

        // Aca declaro que la entrada sea Q negada
        FFD U1(clk, reset, En, ~Q, Q); 
endmodule

Lab_09/Ejercicio02/FlipFlopT_tb.v
// Marco DUarte
// TestBench
// Ejercicio 02

module testbench();

reg clk, reset, En;
wire Q;

FFT FlipFlop(clk, reset, En, Q);

initial begin 
    #1
    $display("----------------------------------------------");
    $display("|  clk  |  Reset  |  En  |  Q  |");
    $monitor("|  %b  |   %b   |  %b  |  %b  |", clk, reset, En, Q);
    clk = 0; reset = 0; En = 0; 
    #2 reset = 1;
    #2 reset = 0;
    #2 En = 1; 
    #4 En = 0;
    #2 En = 1;
end

always
    #1 clk = ~clk;

initial 
    #20 $finish;

initial begin
      $dumpfile("FlipFlopT_tb.vcd");
      $dumpvars(0, testbench);    
end

endmodule

Lab_09/Ejercicio02/FlipFlopT_tb.vcd
$date
	Fri Oct 30 17:40:31 2020
$end
$version
	Icarus Verilog
$end
$timescale
	1ps
$end
$scope module testbench $end
$var wire 1 ! Q $end
$var reg 1 " En $end
$var reg 1 # clk $end
$var reg 1 $ reset $end
$scope module FlipFlop $end
$var wire 1 " En $end
$var wire 1 # clk $end
$var wire 1 $ reset $end
$var wire 1 ! Q $end
$scope module U1 $end
$var wire 1 % D $end
$var wire 1 " En $end
$var wire 1 # clk $end
$var wire 1 $ reset $end
$var reg 1 ! Q $end
$upscope $end
$upscope $end
$upscope $end
$enddefinitions $end
#0
$dumpvars
x%
x$
x#
x"
x!
$end
#1
0"
0$
1#
#2
0#
#3
1%
0!
1#
1$
#4
0#
#5
1#
0$
#6
0#
#7
0%
1!
1#
1"
#8
0#
#9
1%
0!
1#
#10
0#
#11
1#
0"
#12
0#
#13
0%
1!
1#
1"
#14
0#
#15
1%
0!
1#
#16
0#
#17
0%
1!
1#
#18
0#
#19
1%
0!
1#
