Lab_10/Ejercicio02/ALU.v
// Electronica Digital
// Marco Duarte
// Lab_10
// Ejercicio 01
// Union de modulos

module FFD_4(
    input wire Clk, reset, En,
    input wire [3:0]D, 
    output reg [3:0]Q);

    always @ (posedge Clk or posedge reset) begin
        if (reset) 
            Q <= 4'b0000;
        else if (En)
            Q <= D;
    end
endmodule

module BTri(
    input wire En1,
    input wire [3:0]entradas,
    output wire [3:0]salidas);

        assign salidas = (En1) ? entradas:4'bz;
endmodule

module ALU(
    input wire [3:0]A, // Los bits para seleccionar en A
    input wire [3:0]B, // Los bits para seleccionar en B
    input wire [2:0]command, // Aca es donde le damos la instruccion a la ALU
    output reg [3:0]result,
    output reg carry,
    output reg exit); // El resultado de la operacion que se haga

        reg [4:0]q; //Registro que se tiene internamente

        always @ (A or B or command) begin

            // El case sirve para asignarle un valor a cada opcion
            case(command)

                3'b000: begin
                            q = 5'b00000; // Deja pasar A
                            q = A;
                            carry = 1'b0;
                            exit = 1'b0;
                            result = q[3:0];
                        end

                3'b001: begin
                            q[4:0] = 5'b00000; // Deja pasar A
                            q = A - B; // Esta es la accion de comparar
                            carry = q[4];
                            exit = (q == 5'b00000);
                            result = q[3:0];
                        end
                
                3'b010: begin
                            q[4:0] = 5'b00000; // Funciona de reset
                            q = B;
                            carry = 1'b0;
                            exit = 1'b0;
                            result = q[3:0];
                        end

                3'b011: begin
                            q[4:0] = 5'b00000; // Funciona de reset
                            q = A + B;
                            carry = q[4];
                            exit = (q == 5'b00000);
                            result = q[3:0];
                        end

                3'b100: begin
                            q = 5'b00000; // Funciona de reset
                            q = ~(A & B);
                            carry = 1'b0;
                            exit = 1'b0;
                            result = q[3:0];
                        end

            endcase
        end
endmodule

module main(
    input wire [3:0]entradas,
    input wire En1, Clk, reset, En, En2,
    input wire [2:0]command,
    output wire carry, exit,
    output wire [3:0]out);

        wire [3:0]a;
        wire [3:0]b;
        wire [3:0]exit_alu;

        BTri U1(entradas, En1, b);
        FFD_4 U2(Clk, reset, En, exit_alu, a);
        BTri U3(exit_alu, En2, out);
        ALU U4(a, b, command, exit_alu, carry, exit);

endmodule

Lab_10/Ejercicio02/ALU_tb.v
// Marco Duarte
// TestBench
// Ejercicio 02

module testbench();

reg [3:0]entradas;
reg En1, Clk, reset, En, En2;
reg [2:0]command;
wire carry, exit;
wire [3:0]out;

main U0(entradas, En1, Clk, reset, En, En2, command, carry, exit, out);

initial begin
    #1
    $display("-----------------------------------------------------------------------------");
    $display("| Clk | En |  entradas  | Reset | En1 | En2 | command || Carry | Exit | Out |");
    $monitor("|  %b  |  %b |    %b    |   %b   |  %b  |  %b  |   %b   ||   %b   |   %b  | %b|", Clk, En, entradas, reset, En1, En2, command, carry, exit, out);
    entradas = 4'b0000; En1 = 0; Clk = 0; reset = 0; En = 0; En2 = 0; command = 3'b000;
    #2 reset = 1;
    #2 reset = 0;
    #2 entradas = 4'b0001; En1 = 1;
    #2 En = 1; En2 = 1;
    #4 entradas = 4'b0001; command = 3'b001;
    #4 command = 3'b010;
    #2 En = 0;
    #2 En = 1; entradas = 4'b0101;
end

always
    #1 Clk = ~Clk;

initial
    #40 $finish;

initial begin
    $dumpfile("ALU_tb.vcd");
    $dumpvars(0, testbench); 
end

endmodule

Lab_10/Ejercicio02/ALU_tb.vcd
$date
	Sat Nov  7 13:07:38 2020
$end
$version
	Icarus Verilog
$end
$timescale
	1ps
$end
$scope module testbench $end
$var wire 4 ! out [3:0] $end
$var wire 1 " exit $end
$var wire 1 # carry $end
$var reg 1 $ Clk $end
$var reg 1 % En $end
$var reg 1 & En1 $end
$var reg 1 ' En2 $end
$var reg 3 ( command [2:0] $end
$var reg 4 ) entradas [3:0] $end
$var reg 1 * reset $end
$scope module U0 $end
$var wire 1 $ Clk $end
$var wire 1 % En $end
$var wire 1 & En1 $end
$var wire 1 ' En2 $end
$var wire 3 + command [2:0] $end
$var wire 4 , entradas [3:0] $end
$var wire 1 * reset $end
$var wire 4 - out [3:0] $end
$var wire 4 . exit_alu [3:0] $end
$var wire 1 " exit $end
$var wire 1 # carry $end
$var wire 4 / b [3:0] $end
$var wire 4 0 a [3:0] $end
$scope module U1 $end
$var wire 1 1 En1 $end
$var wire 4 2 entradas [3:0] $end
$var wire 4 3 salidas [3:0] $end
$upscope $end
$scope module U2 $end
$var wire 1 $ Clk $end
$var wire 1 % En $end
$var wire 1 * reset $end
$var wire 4 4 D [3:0] $end
$var reg 4 5 Q [3:0] $end
$upscope $end
$scope module U3 $end
$var wire 1 6 En1 $end
$var wire 4 7 entradas [3:0] $end
$var wire 4 8 salidas [3:0] $end
$upscope $end
$scope module U4 $end
$var wire 4 9 A [3:0] $end
$var wire 4 : B [3:0] $end
$var wire 3 ; command [2:0] $end
$var reg 1 # carry $end
$var reg 1 " exit $end
$var reg 5 < q [4:0] $end
$var reg 4 = result [3:0] $end
$upscope $end
$upscope $end
$upscope $end
$enddefinitions $end
#0
$dumpvars
bx =
bx <
bx ;
bx :
bx 9
bx 8
b0x 7
x6
bx 5
bx 4
bx 3
b0x 2
x1
bx 0
bx /
bx .
bx -
bx ,
bx +
x*
bx )
bx (
x'
x&
x%
x$
x#
x"
bx !
$end
#1
0"
0#
b0xxxx <
bz /
bz 3
bz :
01
b0 (
b0 +
b0 ;
b0 7
0'
0%
0*
1$
b0 2
0&
b0 )
b0 ,
#2
0$
#3
bz !
bz -
bz 8
06
b0 .
b0 4
b0 =
b0 <
b0 0
b0 5
b0 9
1$
1*
#4
0$
#5
1$
0*
#6
0$
#7
b1 /
b1 3
b1 :
11
1$
b1 2
1&
b1 )
b1 ,
#8
0$
#9
1$
b1 7
1'
1%
#10
0$
#11
1$
#12
0$
#13
b1111 0
b1111 5
b1111 9
bz !
bz -
bz 8
06
b1110 .
b1110 4
b1110 =
0#
b1110 <
1$
b1 (
b1 +
b1 ;
#14
0$
#15
b1 !
b1 -
b1 8
16
b1101 .
b1101 4
b1101 =
b1101 <
b1110 0
b1110 5
b1110 9
1$
#16
0$
#17
b1 0
b1 5
b1 9
b1 .
b1 4
b1 =
b1 <
1$
b10 (
b10 +
b10 ;
#18
0$
#19
1$
0%
#20
0$
#21
1$
b101 )
b101 ,
1%
