Proyecto_01/3DPrinter.v
// Universidad del Valle de Guatemala
// Electronica Digital 1
// Marco Duarte
// Proyecto # 01 - FSM
// Automatizacion de Impresora 3D - Pre-Impresion

// -------------------------------------------------------------

// FlipFlop de 1 bit
module DFlipFlop(
    input wire clk, reset, D,
    output reg Q);

        always @(posedge clk or posedge reset) begin
            if(reset)begin
            Q <= 1'b0; 
            end

            else
            Q <= D; 
        end
endmodule

// FlipFlop de 2 bit
module D2FlipFlop(
    input wire clk, reset,
    input wire [1:0]D,
    output reg [1:0]Q);

        always @(posedge clk , posedge reset) begin
            if(reset)begin
            Q <= 2'b0; 
            end

            else
            Q <= D; 
        end
endmodule

// FlipFlop de 3 bit
module D3FlipFlop(
    input wire reset, clk,
    input wire [2:0]D,
    output reg [2:0]Q);

        always @ (posedge clk, posedge reset) begin
            if ( reset) begin
                Q <= 3'b0;
            end
            
            else
                Q <= D; 
        end
endmodule

// FlipFlop de 4 bit
module D4FlipFlop(
    input wire reset, clk,
    input wire [3:0]D,
    output reg [3:0]Q);

        always @ (posedge clk, posedge reset) begin
            if ( reset) begin
                Q <= 4'b0;
            end
            
            else
                Q <= D; 
        end
endmodule

// Timer para PLA
module timer01(
    input wire EN,
    output reg T1);

        always @ (EN) begin
            if (EN == 1) begin
                T1 = 0;
                #8
                T1 = 1;
            end

            else
                T1 = 0;
        end
endmodule

// Timer para ABS
module timer02(
    input wire EN0,
    output reg T2);

        always @ (EN0) begin
            if (EN0 == 1) begin
                T2 = 0;
                #10
                T2 = 1;
            end

            else
                T2 = 0;
        end
endmodule

// Timer para TPU
module timer03(
    input wire EN1,
    output reg T3);

        always @ (EN1) begin
            if (EN1 == 1) begin
                T3 = 0;
                #8
                T3 = 1;
            end

            else
                T3 = 0;
        end
endmodule

// --------------- Cajas Negras ---------------

// Maquina de anti-rebote
module Antirebotes(
    input wire clk, reset, signal,
    output wire out);

        wire inc;
        wire ot;

        assign inc = signal;
        assign out = ~ot & signal;

        DFlipFlop AR(clk, reset, signal, out);
endmodule

// Maquina de Control
module Control(
    input wire clk, reset,
    input wire O, I,
    output wire [1:0] C,
    output wire P, P2);

        wire [1:0] S_00;
        wire [1:0] SF_00;
        wire S1, S0;
        wire S1F, S0F;

        assign SF_00 [0] = S0F;
        assign SF_00 [1] = S1F;
    
        // Estados futuros
        assign S1F = (S1 & ~S0 & ~P2) | (~S1 & S0 & I & P);
        assign S0F = (~S1 & ~S0 & O) | (~S1 & S0 & ~I & ~P);


        // Salidas
        assign C [1] = (S1 & ~S0);
        assign C [0] = (~S1 & S0);
        assign P = S0;

        // Conexion al FLIPFLOP
        D2FlipFlop FF00(clk, reset, SF_00, S_00);
endmodule

// Maquina de Motores
module Motores(
    input wire clk, reset, P, sz, sx, sy, sy2, sh, 
    output wire [2:0]M,
    output wire HOME);

        wire [2:0]S_000;
        wire [2:0]SF_000;
        wire S0, S1, S2;
        wire SF0, SF1, SF2;

        assign SF_000[0] = SF0;
        assign SF_000[1] = SF1;
        assign SF_000[2] = SF2;


        // Estados Futuros
        assign SF2 = (S2 & ~S1 & ~S0) | (S2 & ~S1 & ~sh) | (~S2 & S1 & S0 & sy);
        assign SF1 = (~S2 & S1 & ~S0) | (~S2 & S1 & ~sy) | (~S2 & ~S1 & S0 & sz);
        assign SF0 = (~S2 & ~S1 & ~S0 & P) | (S2 & ~S1 & S0 & ~sh) | (~S2 & ~S1 & S0 & ~sz) | (~S2 & S1 & ~S0 & sx) | (~S2 & S1 & S0 & ~sy) | (S2 & ~S1 & ~S0 & sy2);

        // Salidas
        assign M[2] = S2 & ~S1;
        assign M[1] = ~S2 & S1;
        assign M[0] = (~S2 & S0) | (~S1 & S0);
        assign HOME = ~S1;

        // FlipFlop
        D3FlipFlop FF01(clk, reset, SF_000, S_000);
endmodule

module Cama_Hotend(
    input wire clk, reset, PB, sh, T1, T2, T3, AB,
    input wire [1:0]F,
    output wire EN, EN0, EN1, HT,
    output wire [2:0]LCD,
    output wire [1:0]CH,
    output wire [1:0]PH);

        wire [3:0]S_0000;
        wire [3:0]SF_0000;
        wire S0, S1, S2, S3;
        wire SF0, SF1, SF2, SF3;

        assign SF_0000[0] = SF0;
        assign SF_0000[1] = SF1;
        assign SF_0000[2] = SF2;
        assign SF_0000[3] = SF3;
        
        // Estados futuros
        assign SF3 = (S3 & ~S2 & ~S1) | (S3 & ~S2 & ~S0 & ~AB) | (~S2 & ~S1 & S0 & F[1] & F[0]);
        assign SF2 = (~S3 & S2 & ~AB) | (~S3 & S2 & ~S1 & S0) | (~S3 & S2 & S1 & ~S0) | (~S3 & ~S1 & S0 & F[1] & ~F[0]) | (~S3 & ~S2 & S1 & S0 & T1);
        assign SF1 = (~S3 & S1 & ~S0) | (~S3 & ~S2 & S1 & ~T1) | (~S3 & S2 & S1 & ~AB) | (~S2 & S1 & ~S0 & ~AB) | (~S3 & S2 & ~S1 & S0 & T2) | (S3 & ~S2 & ~S1 & S0 & T3) | (~S3 & ~S2 & ~S1 & S0 & ~F[1] & F[0]);
        assign SF0 = (~S3 & ~S2 &  ~S1 & S0 & ~F[0]) | (~S3 & ~S2 & S1 & ~S0 & T1) | (~S3 & ~S2 & S1 & S0 & ~T1) | (~S3 & S2 & S1 & ~S0 & T2) | (~S3 & S2 & ~S1 & S0 & ~T2) | (S3 & ~S2 & ~S1 & ~S0 & T3) | (S3 & ~S2 & ~S1 & S0 & ~T3) | (~S3 & ~S2 & ~S1 & ~S0 & sh & PB) | (~S3 & S2 & S1 & S0 & ~AB);

        // Salidas
        assign LCD[2] = (~S3 & S2 & ~S1) | (~S3 & S2 & S0) | (S3 & ~S2 & ~S0);
        assign LCD[1] = (~S3 & ~S2 & S1) | (S3 & ~S2 & ~S1) | (~S3 & S1 & ~S0);
        assign LCD[0] = (~S3 & ~S2 & S0) | (~S3 & ~S1 & S0) | (~S2 & ~S1 & S0) | (~S3 & S2 & S1 & ~S0);
        assign CH[1] = (~S3 & S2) | (~S2 & ~S1 & ~S0);
        assign CH[0] = (~S2 & ~S0);
        assign PH[0] = (S3 & ~S2 & ~S1) | (~S3 & ~S0);
        assign PH[1] = (S3 & ~S2 & ~S1) | (~S3 & S1 & S0);
        assign EN = ~S3;
        assign EN0 = S3;
        assign EN1 = ~S2 & ~S1;
        assign HT = (~S3 & ~S1) | (~S2 & ~S0) | (~S3 & S2 & S0);

        //FLipFlop
        D4FlipFlop FF10(clk, reset, SF_0000, S_0000);
endmodule

module Indicadores(
    input wire clk, reset, O, P, HT, P2,
    input wire [1:0]PH,
    input wire [1:0]CH,
    output wire [2:0]W);

        wire [2:0]S_000;
        wire [2:0]SF_000;
        wire S0, S1, S2;
        wire SF0, SF1, SF2;

        assign SF_000[0] = SF0;
        assign SF_000[1] = SF1;
        assign SF_000[2] = SF2;

        // Estados Futuros
        assign SF2 = (~S2 & S1 & ~S0 & P) | (S2 & ~S1 & ~S0 & ~HT) | (S2 & ~S1 & S0 & ~P2) | (S2 & S1 & ~S0 & ~P2) | (S2 & ~S1 & ~S0 & PH[1] & PH[0] & CH[1] & CH[0]) | (S2 & ~S1 & ~S0 & PH[1] & ~PH[0] & CH[1] & ~CH[0]);
        assign SF1 = (~S2 & ~S1 & ~S0 & O) | (~S2 & S1 & ~S0 & ~P) | (~S2 & S1 & S0 & ~P2) | (S2 & S1 & ~S0 & ~P2) | (S2 & ~S1 & ~S0 & HT & PH[1] & PH[0] & CH[1] & CH[0]) | (S2 & ~S1 & ~S0 & HT & ~PH[1] & PH[0] & ~CH[1] & CH[0]);
        assign SF0 = (~S2 & S1 & S0 & ~P2) | (S2 & ~S1 & S0 & ~P2) | (S2 & ~S1 & ~S0 & HT & ~PH[1] & PH[0] & ~CH[1] & CH[0]) | (S2 & ~S1 & ~S0 & HT & PH[1] & ~PH[0] & CH[1] & ~CH[0]);

        // Salidas
        assign W[2] = (S2 & ~S1) | (S2 & ~S0);
        assign W[1] = (~S2 & S1) | (S1 & ~S0);
        assign W[0] = (~S2 & S1 & S0) | (S2 & ~S1 & S0);

        //FlipFlop
        D3FlipFlop FF11(clk, reset, SF_000, S_000);
endmodule

module FSM(
    input wire clk, reset, signal, lector, encen, conti, sz, sx, sy, sy2, sh,
    input wire [1:0]F,
    output wire [1:0]C,
    output wire [2:0]LCD,
    output wire [2:0]M,
    output wire [2:0]W);

        wire op, P2, P, HT, EN, EN0, EN1, HOME, T1, T2, T3;
        wire [1:0]CH;
        wire [1:0]PH;

        Antirebotes M001(clk, reset, signal, op);
        Control M010(clk, reset, encen, lector, C, P, P2);
        Motores M011(clk, reset, P, sz, sx, sy, sy2, sh, M, HOME);
        Cama_Hotend M100(clk, reset, PB, HOME, T1, T2, T3, AB, F, EN, EN0, EN1, HT, LCD, CH, PH);
        Indicadores M101(clk, reset, encen, HT, P2, LCD, PH, CH, W);
        timer01 M110(EN, T1);
        timer02 M111(EN0, T2);
        timer03 M000(EN1, T3);
endmodule

Proyecto_01/3DPrinter_tb.v
//TestBench
//Impresora 3D
// Marco DUarte
//19022
// Proyecto # 01 - Digital
// ----------------Modulo Testbench----------------

module testbench();

reg clk, reset, signal, lector, encen, conti, sz, sx, sy, sy2, sh;
reg [1:0]F;
wire [1:0]C;
wire [2:0]LCD;
wire [2:0]M;
wire [2:0]W;

initial begin
   clk <= 1;
   forever #5 clk = ~clk; 
end

//Llamo a mi FSM
FSM main(clk, reset, signal, lector, encen, conti, sz, sx, sy, sy2, sh, F, C, LCD, M, W);


initial begin
    #1
    $display("\n");
    $display("3DPrinter");
    $display("---------------------");
    $monitor("%b %b %b %b %b %b %b %b %b %b %b %b| %b %b %b %b", clk, reset, signal, lector, encen, conti, sz, sx, sy, sy2, sh, F, C, LCD, M, W);

    #3 reset = 1;
    #3 reset = 0;
    #5 signal = 0; lector = 0; encen = 0; conti = 0; sz = 0; sx = 0; sy = 0; sy2 = 0; sh = 0; F = 2'b00;
    #5 signal = 1; lector = 1; encen = 1; conti = 0; sz = 0; sx = 0; sy = 0; sy2 = 0; sh = 0; F = 2'b00;
    #5 signal = 0; lector = 0; encen = 0; conti = 0; sz = 1; sx = 0; sy = 0; sy2 = 0; sh = 0; F = 2'b00;
    #5 signal = 0; lector = 0; encen = 0; conti = 0; sz = 0; sx = 1; sy = 0; sy2 = 0; sh = 0; F = 2'b00;
    #5 signal = 0; lector = 0; encen = 0; conti = 0; sz = 0; sx = 0; sy = 1; sy2 = 0; sh = 0; F = 2'b00;
    #5 signal = 0; lector = 0; encen = 0; conti = 0; sz = 0; sx = 0; sy = 0; sy2 = 1; sh = 0; F = 2'b00;
    #5 signal = 0; lector = 0; encen = 0; conti = 0; sz = 0; sx = 0; sy = 0; sy2 = 0; sh = 1; F = 2'b00;
    #5 signal = 0; lector = 0; encen = 0; conti = 1; sz = 0; sx = 0; sy = 0; sy2 = 0; sh = 0; F = 2'b00;
    #5 signal = 0; lector = 0; encen = 0; conti = 0; sz = 0; sx = 0; sy = 0; sy2 = 0; sh = 0; F = 2'b01;

    #3 reset = 1;
    #3 reset = 0;
    #5 signal = 0; lector = 0; encen = 0; conti = 0; sz = 0; sx = 0; sy = 0; sy2 = 0; sh = 0; F = 2'b00;
    #5 signal = 1; lector = 1; encen = 1; conti = 0; sz = 0; sx = 0; sy = 0; sy2 = 0; sh = 0; F = 2'b00;
    #5 signal = 0; lector = 0; encen = 0; conti = 0; sz = 1; sx = 0; sy = 0; sy2 = 0; sh = 0; F = 2'b00;
    #5 signal = 0; lector = 0; encen = 0; conti = 0; sz = 0; sx = 1; sy = 0; sy2 = 0; sh = 0; F = 2'b00;
    #5 signal = 0; lector = 0; encen = 0; conti = 0; sz = 0; sx = 0; sy = 1; sy2 = 0; sh = 0; F = 2'b00;
    #5 signal = 0; lector = 0; encen = 0; conti = 0; sz = 0; sx = 0; sy = 0; sy2 = 1; sh = 0; F = 2'b00;
    #5 signal = 0; lector = 0; encen = 0; conti = 0; sz = 0; sx = 0; sy = 0; sy2 = 0; sh = 1; F = 2'b00;
    #5 signal = 0; lector = 0; encen = 0; conti = 1; sz = 0; sx = 0; sy = 0; sy2 = 0; sh = 0; F = 2'b00;
    #5 signal = 0; lector = 0; encen = 0; conti = 0; sz = 0; sx = 0; sy = 0; sy2 = 0; sh = 0; F = 2'b10;

end

initial
    #100 $finish;

initial begin
   $dumpfile("3DPrinter_tb.vcd");
   $dumpvars(0, testbench); 
end
endmodule

Proyecto_01/3DPrinter_tb.vcd
$date
	Fri Oct 16 02:57:30 2020
$end
$version
	Icarus Verilog
$end
$timescale
	1ps
$end
$scope module testbench $end
$var wire 3 ! W [2:0] $end
$var wire 3 " M [2:0] $end
$var wire 3 # LCD [2:0] $end
$var wire 2 $ C [1:0] $end
$var reg 2 % F [1:0] $end
$var reg 1 & clk $end
$var reg 1 ' conti $end
$var reg 1 ( encen $end
$var reg 1 ) lector $end
$var reg 1 * reset $end
$var reg 1 + sh $end
$var reg 1 , signal $end
$var reg 1 - sx $end
$var reg 1 . sy $end
$var reg 1 / sy2 $end
$var reg 1 0 sz $end
$scope module main $end
$var wire 1 1 AB $end
$var wire 2 2 F [1:0] $end
$var wire 1 3 P2 $end
$var wire 1 4 PB $end
$var wire 1 & clk $end
$var wire 1 ' conti $end
$var wire 1 ( encen $end
$var wire 1 ) lector $end
$var wire 1 5 op $end
$var wire 1 * reset $end
$var wire 1 + sh $end
$var wire 1 , signal $end
$var wire 1 - sx $end
$var wire 1 . sy $end
$var wire 1 / sy2 $end
$var wire 1 0 sz $end
$var wire 3 6 W [2:0] $end
$var wire 1 7 T3 $end
$var wire 1 8 T2 $end
$var wire 1 9 T1 $end
$var wire 2 : PH [1:0] $end
$var wire 1 ; P $end
$var wire 3 < M [2:0] $end
$var wire 3 = LCD [2:0] $end
$var wire 1 > HT $end
$var wire 1 ? HOME $end
$var wire 1 @ EN1 $end
$var wire 1 A EN0 $end
$var wire 1 B EN $end
$var wire 2 C CH [1:0] $end
$var wire 2 D C [1:0] $end
$scope module M000 $end
$var wire 1 @ EN1 $end
$var reg 1 7 T3 $end
$upscope $end
$scope module M001 $end
$var wire 1 & clk $end
$var wire 1 E inc $end
$var wire 1 F ot $end
$var wire 1 5 out $end
$var wire 1 * reset $end
$var wire 1 , signal $end
$scope module AR $end
$var wire 1 , D $end
$var wire 1 & clk $end
$var wire 1 * reset $end
$var reg 1 G Q $end
$upscope $end
$upscope $end
$scope module M010 $end
$var wire 1 ) I $end
$var wire 1 ( O $end
$var wire 1 ; P $end
$var wire 1 3 P2 $end
$var wire 1 H S0 $end
$var wire 1 I S0F $end
$var wire 1 J S1 $end
$var wire 1 K S1F $end
$var wire 1 & clk $end
$var wire 1 * reset $end
$var wire 2 L S_00 [1:0] $end
$var wire 2 M SF_00 [1:0] $end
$var wire 2 N C [1:0] $end
$scope module FF00 $end
$var wire 2 O D [1:0] $end
$var wire 1 & clk $end
$var wire 1 * reset $end
$var reg 2 P Q [1:0] $end
$upscope $end
$upscope $end
$scope module M011 $end
$var wire 1 ? HOME $end
$var wire 1 ; P $end
$var wire 1 Q S0 $end
$var wire 1 R S1 $end
$var wire 1 S S2 $end
$var wire 1 T SF0 $end
$var wire 1 U SF1 $end
$var wire 1 V SF2 $end
$var wire 1 & clk $end
$var wire 1 * reset $end
$var wire 1 + sh $end
$var wire 1 - sx $end
$var wire 1 . sy $end
$var wire 1 / sy2 $end
$var wire 1 0 sz $end
$var wire 3 W S_000 [2:0] $end
$var wire 3 X SF_000 [2:0] $end
$var wire 3 Y M [2:0] $end
$scope module FF01 $end
$var wire 3 Z D [2:0] $end
$var wire 1 * clk $end
$var wire 1 & reset $end
$var reg 3 [ Q [2:0] $end
$upscope $end
$upscope $end
$scope module M100 $end
$var wire 1 1 AB $end
$var wire 1 B EN $end
$var wire 1 A EN0 $end
$var wire 1 @ EN1 $end
$var wire 2 \ F [1:0] $end
$var wire 1 > HT $end
$var wire 1 4 PB $end
$var wire 1 ] S0 $end
$var wire 1 ^ S1 $end
$var wire 1 _ S2 $end
$var wire 1 ` S3 $end
$var wire 1 a SF0 $end
$var wire 1 b SF1 $end
$var wire 1 c SF2 $end
$var wire 1 d SF3 $end
$var wire 1 7 T3 $end
$var wire 1 & clk $end
$var wire 1 * reset $end
$var wire 1 ? sh $end
$var wire 1 8 T2 $end
$var wire 1 9 T1 $end
$var wire 4 e S_0000 [3:0] $end
$var wire 4 f SF_0000 [3:0] $end
$var wire 2 g PH [1:0] $end
$var wire 3 h LCD [2:0] $end
$var wire 2 i CH [1:0] $end
$scope module FF10 $end
$var wire 4 j D [3:0] $end
$var wire 1 * clk $end
$var wire 1 & reset $end
$var reg 4 k Q [3:0] $end
$upscope $end
$upscope $end
$scope module M101 $end
$var wire 2 l CH [1:0] $end
$var wire 1 3 HT $end
$var wire 1 ( O $end
$var wire 1 > P $end
$var wire 1 m P2 $end
$var wire 2 n PH [1:0] $end
$var wire 1 o S0 $end
$var wire 1 p S1 $end
$var wire 1 q S2 $end
$var wire 1 r SF0 $end
$var wire 1 s SF1 $end
$var wire 1 t SF2 $end
$var wire 1 & clk $end
$var wire 1 * reset $end
$var wire 3 u W [2:0] $end
$var wire 3 v S_000 [2:0] $end
$var wire 3 w SF_000 [2:0] $end
$scope module FF11 $end
$var wire 3 x D [2:0] $end
$var wire 1 * clk $end
$var wire 1 & reset $end
$var reg 3 y Q [2:0] $end
$upscope $end
$upscope $end
$scope module M110 $end
$var wire 1 B EN $end
$var reg 1 9 T1 $end
$upscope $end
$scope module M111 $end
$var wire 1 A EN0 $end
$var reg 1 8 T2 $end
$upscope $end
$upscope $end
$upscope $end
$enddefinitions $end
#0
$dumpvars
b0 y
bx x
bx w
b0 v
bx u
xt
xs
xr
zq
zp
zo
bx n
xm
bx l
b0 k
bx j
bx i
bx h
bx g
bx f
b0 e
xd
xc
xb
xa
z`
z_
z^
z]
bx \
b0 [
bx Z
bx Y
bx X
b0 W
xV
xU
xT
zS
zR
zQ
bx P
bx O
bx N
bx M
bx L
xK
zJ
xI
zH
xG
zF
xE
bx D
bx C
zB
zA
x@
z?
x>
bx =
bx <
z;
bx :
x9
08
x7
bx 6
x5
z4
z3
bx 2
z1
x0
x/
x.
x-
x,
x+
x*
x)
x(
x'
1&
bx %
bx $
bx #
bx "
bx !
$end
#4
b0 L
b0 P
0G
1*
#5
0&
#7
0*
#10
xG
bx L
bx P
1&
#12
b0 %
b0 2
b0 \
0+
0/
0.
0-
00
0'
0(
0)
0E
0,
#15
0&
#17
1(
1)
1E
1,
#20
1G
1&
#22
bx M
bx O
xI
10
0(
0)
0E
0,
#25
0&
#27
1-
00
#30
05
0G
1&
#32
1.
0-
#35
0&
#37
1/
0.
#40
1&
#42
1+
0/
#45
0&
#47
0+
1'
#50
1&
#52
b1 %
b1 2
b1 \
0'
#55
bx v
bx y
bx e
bx k
bx W
bx [
b0 L
b0 P
1*
0&
#58
0*
#60
bx L
bx P
b0 W
b0 [
b0 e
b0 k
b0 v
b0 y
1&
#63
b0 %
b0 2
b0 \
#65
0&
#68
x5
1(
1)
1E
1,
#70
1G
1&
#73
bx M
bx O
xI
10
0(
0)
0E
0,
#75
0&
#78
1-
00
#80
05
0G
1&
#83
1.
0-
#85
0&
#88
1/
0.
#90
1&
#93
1+
0/
#95
0&
#98
0+
1'
