Proyecto_01/3DPrinter.v
// Universidad del Valle de Guatemala
// Electronica Digital 1
// Marco Duarte
// Proyecto # 01 - FSM
// Automatizacion de Impresora 3D - Pre-Impresion

// -------------------------------------------------------------

// FlipFlop de 1 bit
module DFlipFlop(
    input wire clk, reset, D,
    output reg Q);

        always @(posedge clk or posedge reset) begin
            if(reset)begin
            Q <= 1'b0; 
            end

            else
            Q <= D; 
        end
endmodule

// FlipFlop de 2 bit
module D2FlipFlop(
    input wire clk, reset,
    input wire [1:0]D,
    output reg [1:0]Q);

        always @(posedge clk , posedge reset) begin
            if(reset)begin
            Q <= 2'b0; 
            end

            else
            Q <= D; 
        end
endmodule

// FlipFlop de 3 bit
module D3FlipFlop(
    input wire reset, clk,
    input wire [2:0]D,
    output reg [2:0]Q);

        always @ (posedge clk, posedge reset) begin
            if ( reset) begin
                Q <= 3'b0;
            end
            
            else
                Q <= D; 
        end
endmodule

// FlipFlop de 4 bit
module D4FlipFlop(
    input wire reset, clk,
    input wire [3:0]D,
    output reg [3:0]Q);

        always @ (posedge clk, posedge reset) begin
            if ( reset) begin
                Q <= 4'b0;
            end
            
            else
                Q <= D; 
        end
endmodule

// Timer para PLA
module timer01(
    input wire EN,
    output reg T1);

        always @ (EN) begin
            if (EN == 1) begin
                T1 = 0;
                #8
                T1 = 1;
            end

            else
                T1 = 0;
        end
endmodule

// Timer para ABS
module timer02(
    input wire EN0,
    output reg T2);

        always @ (EN0) begin
            if (EN0 == 1) begin
                T2 = 0;
                #10
                T2 = 1;
            end

            else
                T2 = 0;
        end
endmodule

// Timer para TPU
module timer03(
    input wire EN1,
    output reg T3);

        always @ (EN1) begin
            if (EN1 == 1) begin
                T3 = 0;
                #8
                T3 = 1;
            end

            else
                T3 = 0;
        end
endmodule

module counterGG(
    input wire clk, reset,
    input wire [7:0]maxvalue,
    output reg zero,
    output reg [7:0]value);

        always @ (posedge clk, posedge reset) begin
        if (reset) begin
            value <= 8'b0;
            zero <= 1'b0;
         end
        else if (value < maxvalue) begin
            value <= value + 1;
            zero <= 1'b0;
         end
        else if (value == maxvalue) begin
            value <= 8'b0;
            zero <= 1'b1;
         end
        end
endmodule

module timerGG( 
    input wire clk, EN,
    output wire T1);


    wire clock, zero;
    wire [7:0]value;

    assign clock = clk & EN;

    counterGG T_1(clock, ~EN, 8'b00000101, zero, value);
    DFlipFlop T_2(zero, ~EN, 1'b1, T1);
endmodule

// --------------- Cajas Negras ---------------

// Maquina de anti-rebote
module Antirebotes(
    input wire clk, reset, signal,
    output wire out);

        wire inc;
        wire ot;

        assign inc = signal;
        assign out = ~ot & signal;

        DFlipFlop AR(clk, reset, inc, ot);
endmodule

// Maquina de Control
/*module Control(
    input wire clk, reset,
    input wire O, I, R, P2,
    output wire [1:0]C,
    output wire P);

        wire [1:0]S_00;
        wire [1:0]SF_00;
        wire S1, S0;

        assign S0 = S_00[0];
        assign S1 = S_00[1];

        // Estados futuros
        assign SF_00[1] = (S1 & ~S0 & ~P2) | (~S1 & S0 & I & R);
        assign SF_00[0] = (~S1 & ~S0 & O) | (~S1 & S0 & ~I & ~R);


        // Salidas
        assign C[1] = (~S1 & S0);
        assign C[0] = (S1 & ~S0);
        assign P = ~S0;

        // Conexion al FLIPFLOP
        D2FlipFlop FF00(clk, reset, SF_00, S_00);
endmodule
*/

module Control(
    input wire clk, reset, 
    input wire O, I, R, P2,
    output wire [1:0]C,
    output wire P);

        wire [1:0]S_00;
        wire [1:0]SF_00;
        wire S1, S0;

        assign S0 = S_00[0];
        assign S1 = S_00[1];

        assign SF_00[1] = (~S1 & S0 & O & I & ~P2 & R) | (S1 & ~S0 & O & I & ~P2 & R);
        assign SF_00[0] = (~S1 & O & ~I & ~P2 & ~R);

        // Salidas
        assign C[1] = (~S1 & S0);
        assign C[0] = (S1 & ~S0);
        assign P = ~S0;

        // Conexion al FLIPFLOP
        D2FlipFlop FF00(clk, reset, SF_00, S_00);
endmodule

// Maquina de Motores
module Motores(
    input wire clk, reset, P, sz, sx, sy, sy2, sh, 
    output wire [2:0]M,
    output wire HOME);

        wire [2:0]S_000;
        wire [2:0]SF_000;
        wire S0, S1, S2;

        assign S0 = S_000[0];
        assign S1 = S_000[1];
        assign S2 = S_000[2];


        // Estados Futuros
        assign SF_000[2] = (S2 & ~S1 & ~S0) | (S2 & ~S1 & ~sh) | (~S2 & S1 & S0 & sy);
        assign SF_000[1] = (~S2 & S1 & ~S0) | (~S2 & S1 & ~sy) | (~S2 & ~S1 & S0 & sz);
        assign SF_000[0] = (~S2 & ~S1 & ~S0 & P) | (S2 & ~S1 & S0 & ~sh) | (~S2 & ~S1 & S0 & ~sz) | (~S2 & S1 & ~S0 & sx) | (~S2 & S1 & S0 & ~sy) | (S2 & ~S1 & ~S0 & sy2);

        // Salidas
        assign M[2] = (S2 & ~S1);
        assign M[1] = (~S2 & S1);
        assign M[0] = (~S2 & S0) | (~S1 & S0);
        assign HOME = ~S1;

        // FlipFlop
        D3FlipFlop FF01(clk, reset, SF_000, S_000);
endmodule

// Maquina de Cama/Hotend
module Cama_Hotend(
    input wire clk, reset, PB, sh, T1, AB,
    input wire [1:0]F,
    output wire EN, HT,
    output wire [2:0]LCD,
    output wire [1:0]CH,
    output wire [1:0]PH);

        wire [3:0]S_0000;
        wire [3:0]SF_0000;
        wire S0, S1, S2, S3;

        assign S0 = S_0000[0];
        assign S1 = S_0000[1];
        assign S2 = S_0000[2];
        assign S3 = S_0000[3];
        
        // Estados futuros
        assign SF_0000[3] = (S3 & ~S2 & ~S1) | (S3 & ~S2 & ~S0 & ~AB) | (~S2 & ~S1 & S0 & F[1] & F[0]);
        assign SF_0000[2] = (~S3 & S2 & ~AB) | (~S3 & S2 & ~S1 & S0) | (~S3 & S2 & S1 & ~S0) | (~S3 & ~S1 & S0 & F[1] & ~F[0]) | (~S3 & ~S2 & S1 & S0 & T1);
        assign SF_0000[1] = (~S3 & S1 & ~S0) | (~S3 & ~S2 & S1 & ~T1) | (~S3 & S2 & S1 & ~AB) | (~S2 & S1 & ~S0 & ~AB) | (~S3 & S2 & ~S1 & S0 & T1) | (S3 & ~S2 & ~S1 & S0 & T1) | (~S3 & ~S2 & ~S1 & S0 & ~F[1] & F[0]);
        assign SF_0000[0] = (~S3 & ~S2 &  ~S1 & S0 & ~F[0]) | (~S3 & ~S2 & S1 & ~S0 & T1) | (~S3 & ~S2 & S1 & S0 & ~T1) | (~S3 & S2 & S1 & ~S0 & T1) | (~S3 & S2 & ~S1 & S0 & ~T1) | (S3 & ~S2 & ~S1 & ~S0 & T1) | (S3 & ~S2 & ~S1 & S0 & ~T1) | (~S3 & ~S2 & ~S1 & ~S0 & sh & PB) | (~S3 & S2 & S1 & S0 & ~AB);

        //FLipFlop
        D4FlipFlop FF10(clk, reset, SF_0000, S_0000);

        // Salidas
        assign LCD[2] = (~S3 & S2 & ~S1) | (~S3 & S2 & S0) | (S3 & ~S2 & ~S0);
        assign LCD[1] = (~S3 & ~S2 & S1) | (S3 & ~S2 & ~S1) | (~S3 & S1 & ~S0);
        assign LCD[0] = (~S3 & ~S2 & S0) | (~S3 & ~S1 & S0) | (~S2 & ~S1 & S0) | (~S3 & S2 & S1 & ~S0);
        assign CH[1] = (~S3 & S2) | (~S2 & ~S1 & ~S0);
        assign CH[0] = (~S2 & ~S0);
        assign PH[0] = (S3 & ~S2 & ~S1) | (~S3 & ~S0);
        assign PH[1] = (S3 & ~S2 & ~S1) | (~S3 & S1 & S0);
        assign EN = ~S3;
        assign HT = (~S3 & ~S1) | (~S2 & ~S0) | (~S3 & S2 & S0);

        
endmodule

// Maquina de Indicadores
module Indicadores(
    input wire clk, reset, O, P, HT, P2,
    input wire [1:0]PH,
    input wire [1:0]CH,
    output wire [2:0]W);

        wire [2:0]S_000;
        wire [2:0]SF_000;
        wire S0, S1, S2;

        assign S0 = S_000[0];
        assign S1 = S_000[1];
        assign S2 = S_000[2];

        // Estados Futuros
        assign SF_000[2] = (~S2 & S1 & ~S0 & P) | (S2 & ~S1 & ~S0 & ~HT) | (S2 & ~S1 & S0 & ~P2) | (S2 & S1 & ~S0 & ~P2) | (S2 & ~S1 & ~S0 & PH[1] & PH[0] & CH[1] & CH[0]) | (S2 & ~S1 & ~S0 & PH[1] & ~PH[0] & CH[1] & ~CH[0]);
        assign SF_000[1] = (~S2 & ~S1 & ~S0 & O) | (~S2 & S1 & ~S0 & ~P) | (~S2 & S1 & S0 & ~P2) | (S2 & S1 & ~S0 & ~P2) | (S2 & ~S1 & ~S0 & HT & PH[1] & PH[0] & CH[1] & CH[0]) | (S2 & ~S1 & ~S0 & HT & ~PH[1] & PH[0] & ~CH[1] & CH[0]);
        assign SF_000[0] = (~S2 & S1 & S0 & ~P2) | (S2 & ~S1 & S0 & ~P2) | (S2 & ~S1 & ~S0 & HT & ~PH[1] & PH[0] & ~CH[1] & CH[0]) | (S2 & ~S1 & ~S0 & HT & PH[1] & ~PH[0] & CH[1] & ~CH[0]);

        //FlipFlop
        D3FlipFlop FF11(clk, reset, SF_000, S_000);

        // Salidas
        assign W[2] = (S2 & ~S1) | (S2 & ~S0);
        assign W[1] = (~S2 & S1) | (S1 & ~S0);
        assign W[0] = (~S2 & S1 & S0) | (S2 & ~S1 & S0);


endmodule

// Maquina Main
module FSM(
    input wire clk, reset, signal, I, O, P2, PB, sz, sx, sy, sy2, sh, AB,
    input wire [1:0]F,
    output wire [1:0]C,
    output wire [2:0]LCD,
    output wire [2:0]M,
    output wire [2:0]W);

        wire ot, HT, EN, HOME, T1, P;
        wire [1:0]CH;
        wire [1:0]PH;

        Antirebotes M001(clk, reset, signal, ot);
        Control M010(clk, reset, O, I, ot, P2, C, P);
        Motores M011(clk, reset, ot, sz, sx, sy, sy2, sh, M, HOME);
        Cama_Hotend M100(clk, reset, PB, HOME, T1, AB, F, EN, HT, LCD, CH, PH);
        Indicadores M101(clk, reset, O, ot, HT, P2, PH, CH, W);
        /*
        timer01 M110(EN, T1);
        timer02 M111(EN0, T2);
        timer03 M000(EN1, T3);
        */
        timerGG M111(clk, EN, T1);
endmodule

Proyecto_01/3DPrinter_tb.v
//TestBench
//Impresora 3D
// Marco DUarte
//19022
// Proyecto # 01 - Digital
// ----------------Modulo Testbench----------------

module testbench();

reg clk, reset, signal, I, O, P2, PB, sz, sx, sy, sy2, sh, AB;
reg [1:0]F;
wire [1:0]C;
wire [2:0]LCD;
wire [2:0]M;
wire [2:0]W;

initial begin
   clk <= 1;
   forever #5 clk = ~clk; 
end

//Llamo a mi FSM
FSM main(clk, reset, signal, I, O, P2, PB, sz, sx, sy, sy2, sh, AB, F, C, LCD, M, W);


initial begin
    #1
    $display("\n");
    $display("3DPrinter");
    $display("---------------------");
    $display("Clk r s I O P2 PB sz sx sy sy2 sh  AB  F ");
    $monitor("%b   %b %b %b %b %b %b  %b  %b  %b  %b  %b   %b  %b  ", clk, reset, signal, I, O, P2, PB, sz, sx, sy, sy2, sh, AB, F);

    #3 reset = 1;
    #3 reset = 0;
    #2 AB = 0; P2 = 0;
    #5 signal = 0; I = 0; O = 0; PB = 0; sz = 0; sx = 0; sy = 0; sy2 = 0; sh = 0; F = 2'b00;
    #5 signal = 1; I = 1; O = 1; PB = 0; sz = 0; sx = 0; sy = 0; sy2 = 0; sh = 0; F = 2'b00;
    #5 signal = 0; I = 0; O = 0; PB = 0; sz = 1; sx = 0; sy = 0; sy2 = 0; sh = 0; F = 2'b00;
    #5 signal = 0; I = 0; O = 0; PB = 0; sz = 0; sx = 1; sy = 0; sy2 = 0; sh = 0; F = 2'b00;
    #5 signal = 0; I = 0; O = 0; PB = 0; sz = 0; sx = 0; sy = 1; sy2 = 0; sh = 0; F = 2'b00;
    #5 signal = 0; I = 0; O = 0; PB = 0; sz = 0; sx = 0; sy = 0; sy2 = 1; sh = 0; F = 2'b00;
    #5 signal = 0; I = 0; O = 0; PB = 0; sz = 0; sx = 0; sy = 0; sy2 = 0; sh = 1; F = 2'b00;
    #5 signal = 0; I = 0; O = 0; PB = 1; sz = 0; sx = 0; sy = 0; sy2 = 0; sh = 0; F = 2'b00;
    #5 signal = 0; I = 0; O = 0; PB = 0; sz = 0; sx = 0; sy = 0; sy2 = 0; sh = 0; F = 2'b01;

    #3 reset = 1;
    #3 reset = 0;
    #5 signal = 0; I = 0; O = 0; PB = 0; sz = 0; sx = 0; sy = 0; sy2 = 0; sh = 0; F = 2'b00;
    #5 signal = 1; I = 1; O = 1; PB = 0; sz = 0; sx = 0; sy = 0; sy2 = 0; sh = 0; F = 2'b00;
    #5 signal = 0; I = 0; O = 0; PB = 0; sz = 1; sx = 0; sy = 0; sy2 = 0; sh = 0; F = 2'b00;
    #5 signal = 0; I = 0; O = 0; PB = 0; sz = 0; sx = 1; sy = 0; sy2 = 0; sh = 0; F = 2'b00;
    #5 signal = 0; I = 0; O = 0; PB = 0; sz = 0; sx = 0; sy = 1; sy2 = 0; sh = 0; F = 2'b00;
    #5 signal = 0; I = 0; O = 0; PB = 0; sz = 0; sx = 0; sy = 0; sy2 = 1; sh = 0; F = 2'b00;
    #5 signal = 0; I = 0; O = 0; PB = 0; sz = 0; sx = 0; sy = 0; sy2 = 0; sh = 1; F = 2'b00;
    #5 signal = 0; I = 0; O = 0; PB = 1; sz = 0; sx = 0; sy = 0; sy2 = 0; sh = 0; F = 2'b00;
    #5 signal = 0; I = 0; O = 0; PB = 0; sz = 0; sx = 0; sy = 0; sy2 = 0; sh = 0; F = 2'b10;

    #3 reset = 1;
    #3 reset = 0;
    #5 signal = 0; I = 0; O = 0; PB = 0; sz = 0; sx = 0; sy = 0; sy2 = 0; sh = 0; F = 2'b00;
    #5 signal = 1; I = 1; O = 1; PB = 0; sz = 0; sx = 0; sy = 0; sy2 = 0; sh = 0; F = 2'b00;
    #5 signal = 0; I = 0; O = 0; PB = 0; sz = 1; sx = 0; sy = 0; sy2 = 0; sh = 0; F = 2'b00;
    #5 signal = 0; I = 0; O = 0; PB = 0; sz = 0; sx = 1; sy = 0; sy2 = 0; sh = 0; F = 2'b00;
    #5 signal = 0; I = 0; O = 0; PB = 0; sz = 0; sx = 0; sy = 1; sy2 = 0; sh = 0; F = 2'b00;
    #5 signal = 0; I = 0; O = 0; PB = 0; sz = 0; sx = 0; sy = 0; sy2 = 1; sh = 0; F = 2'b00;
    #5 signal = 0; I = 0; O = 0; PB = 0; sz = 0; sx = 0; sy = 0; sy2 = 0; sh = 1; F = 2'b00;
    #5 signal = 0; I = 0; O = 0; PB = 1; sz = 0; sx = 0; sy = 0; sy2 = 0; sh = 0; F = 2'b00;
    #5 signal = 0; I = 0; O = 0; PB = 0; sz = 0; sx = 0; sy = 0; sy2 = 0; sh = 0; F = 2'b11;

end

initial
    #165 $finish;

initial begin
   $dumpfile("3DPrinter_tb.vcd");
   $dumpvars(0, testbench); 
end
endmodule

Proyecto_01/3DPrinter_tb.vcd
$date
	Sat Oct 17 17:19:50 2020
$end
$version
	Icarus Verilog
$end
$timescale
	1ps
$end
$scope module testbench $end
$var wire 3 ! W [2:0] $end
$var wire 3 " M [2:0] $end
$var wire 3 # LCD [2:0] $end
$var wire 2 $ C [1:0] $end
$var reg 1 % AB $end
$var reg 2 & F [1:0] $end
$var reg 1 ' I $end
$var reg 1 ( O $end
$var reg 1 ) P2 $end
$var reg 1 * PB $end
$var reg 1 + clk $end
$var reg 1 , reset $end
$var reg 1 - sh $end
$var reg 1 . signal $end
$var reg 1 / sx $end
$var reg 1 0 sy $end
$var reg 1 1 sy2 $end
$var reg 1 2 sz $end
$scope module main $end
$var wire 1 % AB $end
$var wire 2 3 F [1:0] $end
$var wire 1 ' I $end
$var wire 1 ( O $end
$var wire 1 ) P2 $end
$var wire 1 * PB $end
$var wire 1 + clk $end
$var wire 1 , reset $end
$var wire 1 - sh $end
$var wire 1 . signal $end
$var wire 1 / sx $end
$var wire 1 0 sy $end
$var wire 1 1 sy2 $end
$var wire 1 2 sz $end
$var wire 1 4 ot $end
$var wire 3 5 W [2:0] $end
$var wire 1 6 T1 $end
$var wire 2 7 PH [1:0] $end
$var wire 1 8 P $end
$var wire 3 9 M [2:0] $end
$var wire 3 : LCD [2:0] $end
$var wire 1 ; HT $end
$var wire 1 < HOME $end
$var wire 1 = EN $end
$var wire 2 > CH [1:0] $end
$var wire 2 ? C [1:0] $end
$scope module M001 $end
$var wire 1 + clk $end
$var wire 1 @ inc $end
$var wire 1 4 out $end
$var wire 1 , reset $end
$var wire 1 . signal $end
$var wire 1 A ot $end
$scope module AR $end
$var wire 1 @ D $end
$var wire 1 + clk $end
$var wire 1 , reset $end
$var reg 1 A Q $end
$upscope $end
$upscope $end
$scope module M010 $end
$var wire 1 ' I $end
$var wire 1 ( O $end
$var wire 1 8 P $end
$var wire 1 ) P2 $end
$var wire 1 4 R $end
$var wire 1 + clk $end
$var wire 1 , reset $end
$var wire 2 B S_00 [1:0] $end
$var wire 2 C SF_00 [1:0] $end
$var wire 1 D S1 $end
$var wire 1 E S0 $end
$var wire 2 F C [1:0] $end
$scope module FF00 $end
$var wire 2 G D [1:0] $end
$var wire 1 + clk $end
$var wire 1 , reset $end
$var reg 2 H Q [1:0] $end
$upscope $end
$upscope $end
$scope module M011 $end
$var wire 1 < HOME $end
$var wire 1 4 P $end
$var wire 1 + clk $end
$var wire 1 , reset $end
$var wire 1 - sh $end
$var wire 1 / sx $end
$var wire 1 0 sy $end
$var wire 1 1 sy2 $end
$var wire 1 2 sz $end
$var wire 3 I S_000 [2:0] $end
$var wire 3 J SF_000 [2:0] $end
$var wire 1 K S2 $end
$var wire 1 L S1 $end
$var wire 1 M S0 $end
$var wire 3 N M [2:0] $end
$scope module FF01 $end
$var wire 3 O D [2:0] $end
$var wire 1 , clk $end
$var wire 1 + reset $end
$var reg 3 P Q [2:0] $end
$upscope $end
$upscope $end
$scope module M100 $end
$var wire 1 % AB $end
$var wire 1 = EN $end
$var wire 2 Q F [1:0] $end
$var wire 1 ; HT $end
$var wire 1 * PB $end
$var wire 1 + clk $end
$var wire 1 , reset $end
$var wire 1 < sh $end
$var wire 1 6 T1 $end
$var wire 4 R S_0000 [3:0] $end
$var wire 4 S SF_0000 [3:0] $end
$var wire 1 T S3 $end
$var wire 1 U S2 $end
$var wire 1 V S1 $end
$var wire 1 W S0 $end
$var wire 2 X PH [1:0] $end
$var wire 3 Y LCD [2:0] $end
$var wire 2 Z CH [1:0] $end
$scope module FF10 $end
$var wire 4 [ D [3:0] $end
$var wire 1 , clk $end
$var wire 1 + reset $end
$var reg 4 \ Q [3:0] $end
$upscope $end
$upscope $end
$scope module M101 $end
$var wire 2 ] CH [1:0] $end
$var wire 1 ; HT $end
$var wire 1 ( O $end
$var wire 1 4 P $end
$var wire 1 ) P2 $end
$var wire 2 ^ PH [1:0] $end
$var wire 1 + clk $end
$var wire 1 , reset $end
$var wire 3 _ W [2:0] $end
$var wire 3 ` S_000 [2:0] $end
$var wire 3 a SF_000 [2:0] $end
$var wire 1 b S2 $end
$var wire 1 c S1 $end
$var wire 1 d S0 $end
$scope module FF11 $end
$var wire 3 e D [2:0] $end
$var wire 1 , clk $end
$var wire 1 + reset $end
$var reg 3 f Q [2:0] $end
$upscope $end
$upscope $end
$scope module M111 $end
$var wire 1 = EN $end
$var wire 1 + clk $end
$var wire 1 g clock $end
$var wire 1 h zero $end
$var wire 8 i value [7:0] $end
$var wire 1 6 T1 $end
$scope module T_1 $end
$var wire 1 g clk $end
$var wire 8 j maxvalue [7:0] $end
$var wire 1 k reset $end
$var reg 8 l value [7:0] $end
$var reg 1 h zero $end
$upscope $end
$scope module T_2 $end
$var wire 1 m D $end
$var wire 1 h clk $end
$var wire 1 n reset $end
$var reg 1 6 Q $end
$upscope $end
$upscope $end
$upscope $end
$upscope $end
$enddefinitions $end
#0
$dumpvars
0n
1m
bx l
0k
b101 j
bx i
xh
1g
b0 f
b0x0 e
0d
0c
0b
b0x0 a
b0 `
b0 _
b1 ^
b11 ]
b0 \
b0x [
b11 Z
b0 Y
b1 X
0W
0V
0U
0T
b0x S
b0 R
bx Q
b0 P
b0x O
b0 N
0M
0L
0K
b0x J
b0 I
bx H
bx G
bx F
xE
xD
bx C
bx B
xA
x@
bx ?
b11 >
1=
1<
1;
b0 :
b0 9
x8
b1 7
x6
b0 5
x4
bx 3
x2
x1
x0
x/
x.
x-
x,
1+
x*
x)
x(
x'
bx &
x%
bx $
b0 #
b0 "
b0 !
$end
#4
b0x C
b0x G
18
b0 $
b0 ?
b0 F
0D
0E
b0 B
b0 H
0A
1,
#5
0g
0+
#7
0,
#9
0)
0%
#10
bx C
bx G
x8
bx0 $
bx0 ?
bx0 F
xE
xA
b0x B
b0x H
1g
1+
#14
b0 J
b0 O
b0 a
b0 e
b0 S
b0 [
b0 C
b0 G
04
b0 &
b0 3
b0 Q
0-
01
00
0/
02
0*
0(
0'
0@
0.
#15
0g
0+
#19
b0x J
b0x O
b10 a
b10 e
bx0 C
bx0 G
x4
1(
1'
1@
1.
#20
b0 J
b0 O
b0 C
b0 G
18
b0x $
b0x ?
b0x F
04
xD
0E
bx0 B
bx0 H
1A
1g
1+
#24
b0 a
b0 e
12
0(
0'
0@
0.
#25
0g
0+
#29
1/
02
#30
b0 $
b0 ?
b0 F
0D
0A
b0 B
b0 H
1g
1+
#34
10
0/
#35
0g
0+
#39
11
00
#40
1g
1+
#44
1-
01
#45
0g
0+
#49
b1 S
b1 [
0-
1*
#50
1g
1+
#54
b0 S
b0 [
b1 &
b1 3
b1 Q
0*
#55
0g
0+
#57
1,
#60
1g
0,
1+
#65
0g
b0 &
b0 3
b0 Q
0+
#70
1A
b0 J
b0 O
b10 a
b10 e
04
1g
1(
1'
1@
1.
1+
#75
b0 a
b0 e
0g
12
0(
0'
0@
0.
0+
#80
0A
1g
1/
02
1+
#85
0g
10
0/
0+
#90
1g
11
00
1+
#95
0g
1-
01
0+
#100
b1 S
b1 [
1g
0-
1*
1+
#105
b0 S
b0 [
0g
b10 &
b10 3
b10 Q
0*
0+
#108
1,
#110
1g
1+
#111
0,
#115
0g
0+
#116
b0 &
b0 3
b0 Q
#120
1g
1+
#121
b1 J
b1 O
b10 a
b10 e
14
1(
1'
1@
1.
#125
0g
0+
#126
b0 J
b0 O
b0 a
b0 e
04
12
0(
0'
0@
0.
#130
1g
1+
#131
1/
02
#135
0g
0+
#136
10
0/
#140
1g
1+
#141
11
00
#145
0g
0+
#146
1-
01
#150
1g
1+
#151
b1 S
b1 [
0-
1*
#155
0g
0+
#156
b0 S
b0 [
b11 &
b11 3
b11 Q
0*
