03_Tabla_POS/POS_03.v
// Marco Duarte - 19022
// POS tabla_03

module Lab_03();

// Declaracion de variables por modulo del circuito

wire N1, N2, N3, N4; // Not del circuito
wire O1, O2, O3, O4, O5, O6, O7, O8, O9; // Or del circutio
wire A1; // And del circuito

reg inA, inB, inC, inD; // Declarando que el circuito tiene 3 entradas

//Declaracion de compuertas

not NA (N1,   inA); // A not
not NB (N2,   inB); // B not
not NC (N3,   inC); // C not
not ND (N4,   inD); // D not
or OA (O1,    inA, N2, inC, inD); //Las 4 entradas del Or_1
or OB (O2,    inA, N2, inC, N4); // Las 4 entradas del Or_2
or OC (O3,    inA, N2, N3, inD); // Las 4 entradas del Or_3
or OD (O4,    inA, N2, N3, N4); // Las 4 entradas del Or_3
or OE (O5,    N1, inB, inC, N4); // Las 4 entradas del Or_3
or OE (O6,    N1, inB, N3, N4); // Las 4 entradas del Or_3
or OE (O7,    N1, N2, inC, inD); // Las 4 entradas del Or_3
or OE (O8,    N1, N2, inC, N4); // Las 4 entradas del Or_3
or OE (O9,    N1, N2, N3, N4); // Las 4 entradas del Or_3
and A0 (A1,   O1, O2, O3, O4, O5, O6, O7, O8, O9); // Las 9 entradas del And

initial // Inicio el codigo luego de establecer las condiciones
  begin
    $display("A B C| Y");
    $display("-------");
    $monitor("%b %b %b %b | %b", inA, inB, inC, inD,  A1);

// Inputs en 0
inA = 0; inB = 0; inC = 0; inD = 0;

// Declaramos los cambios en los tiempos
// #1 marca un retardo de una unidad de tiempo
#1 inD = 1;
#1 inC = 1; inD = 0;
#1 inD = 1;
#1 inB = 1; inC = 0; inD = 0;
#1 inD = 1;
#1 inC = 1; inD = 0;
#1 inD = 1;
#1 inA = 1; inB = 0; inC = 0; inD = 0;
#1 inD = 1;
#1 inC = 1; inD = 0;
#1 inD = 1;
#1 inB = 1; inC = 0; inD = 0;
#1 inD = 1;
#1 inC = 1; inD = 0;
#1 inD = 1;
#1 $finish; // termina la simulacion
end

initial
  begin
    $dumpfile("POS_03_tb.vcd");
    $dumpvars(0, Lab_03);
  end
endmodule //finalizar el modulo

03_Tabla_POS/POS_03_tb.vcd
$date
	Sat Aug 01 22:23:51 2020
$end
$version
	Icarus Verilog
$end
$timescale
	1ps
$end
$scope module Lab_03 $end
$var wire 1 ! A1 $end
$var wire 1 " N1 $end
$var wire 1 # N2 $end
$var wire 1 $ N3 $end
$var wire 1 % N4 $end
$var wire 1 & O1 $end
$var wire 1 ' O2 $end
$var wire 1 ( O3 $end
$var wire 1 ) O4 $end
$var wire 1 * O5 $end
$var wire 1 + O6 $end
$var wire 1 , O7 $end
$var wire 1 - O8 $end
$var wire 1 . O9 $end
$var reg 1 / inA $end
$var reg 1 0 inB $end
$var reg 1 1 inC $end
$var reg 1 2 inD $end
$upscope $end
$enddefinitions $end
#0
$dumpvars
02
01
00
0/
1.
1-
1,
1+
1*
1)
1(
1'
1&
1%
1$
1#
1"
1!
$end
#1
0%
12
#2
1%
0$
02
11
#3
0%
12
#4
0!
1%
1'
0&
1$
0#
02
01
10
#5
0'
1&
0%
12
#6
0(
1%
1'
0$
02
11
#7
0)
1(
0%
12
#8
1!
1%
1$
1+
1*
1#
1)
0"
02
01
00
1/
#9
0!
0*
0%
12
#10
1!
1%
1*
0$
02
11
#11
0!
0+
0%
12
#12
1%
1-
0,
1$
1+
0#
02
01
10
#13
0-
1,
0%
12
#14
1!
1%
1-
0$
02
11
#15
0!
0.
0%
12
