Lab_04/Gate_level/GatesLevel.v
// Todos los modulos
// Marco Duarte
// 19022
module Gates_Level_01(input wire inA, inB, inC, inD, output wire Y);

    // Declaracion de variables por modulo del circuito

    wire N1, N2, N3, N4;                  // Not del circuito
    wire A1, A2, A3, A4, A5, A6, A7, A8;  // And del circuito
   
    //Declaracion de compuertas

    not NA (N1,   inA); // A not
    not NB (N2,   inB); // B not
    not NC (N3,   inC); // C not
    not ND (N4,   inD); // D not
    and AA (A1,   N1, N2, N3, N4); // Las 4 entradas del And
    and AB (A2,   N1, N2, inC, inD); // Las 4 entradas del And
    and AC (A3,   N1, inB, N3, inD); // Las 4 entradas del And
    and AD (A4,   N1, inB, inC, N4); // Las 4 entradas del And
    and AE (A5,   inA, inB, N3, N4); // Las 4 entradas del And
    and AF (A6,   inA, inB, inC, inD); // Las 4 entradas del And
    and AG (A7,   inA, N2, N3, inD); // Las 4 entradas del And
    and AG (A8,   inA, N2, inC, N4); // Las 4 entradas del And
    or O0 (Y,    A1, A2, A3, A4, A5, A6, A7, A8); //Las 8 entradas del Or_1

endmodule //finalizar el modulo

module Gates_Level_02(input wire inA, inB, inC, output wire Y);

    // Declaracion de variables por modulo del circuito

    wire N1;                  // Not del circuito

    //Declaracion de compuertas

    not NB (N1,   inB); // B not
    and AA (Y, N1);

endmodule //finalizar el modulo

module Gates_Level_03(input wire inA, inB, inC, output wire Y);

    // Declaracion de variables por modulo del circuito

    wire N2;                  // Not del circuito
    wire A1, A2;

    //Declaracion de compuertas

    not NB (N2,     inB); // B not
    and AA (A1,     N2);
    and AB (A2,     inB, inC);
    or O0 (Y,      A1, A2);

endmodule //finalizar el modulo

module Gates_Level_04(input wire inA, inB, inC, output wire Y);

    // Declaracion de variables por modulo del circuito

    wire N1, N3;                  // Not del circuito
    wire A1, A2;

    //Declaracion de compuertas

    not NA (N1,     inA); // B not
    not NC (N3,     inC);
    and AA (A1,     N1, N3);
    and AB (A2,     inB);
    or O0 (Y,      A1, A2);

endmodule //finalizar el modulo

Lab_04/Gate_level/GatesLevel_tb.v
// Modulo para llamar a GatesLevel.v
//TestBench

module testbench();

//Variables para modulos 
reg p1, p2, p3, p4, p5, p6, p7, p8, p9, p10, p11, p12, p13;
wire out1, out2, out3, out4;

Gates_Level_01 G1(p1, p2, p3, p4, out1); //Configuracion del modulo Gates_Level_01
Gates_Level_02 G2(p5, p6, p7, out2); // Configuracion para mi modulo 2
Gates_Level_03 G3(p8, p9, p10, out3); // Configuracion para mi modulo 3
Gates_Level_04 G4(p11, p12, p13, out4); // Configuracion para mi modulo 4

// Se llaman los modulos del archivo .v
// Se les pone tiempo

initial begin // Display de la tabla de verdad modulo 1
    $display("A B C D | Y");
    $display("--------|--");
    $monitor("%b %b %b %b | %b", p1, p2, p3, p4, out1);
     p1 = 0; p2 = 0; p3 = 0; p4 = 0; 
  #1 p1 = 0; p2 = 0; p3 = 0; p4 = 1;
  #1 p1 = 0; p2 = 0; p3 = 1; p4 = 0;
  #1 p1 = 0; p2 = 0; p3 = 1; p4 = 1;
  #1 p1 = 0; p2 = 1; p3 = 0; p4 = 0;
  #1 p1 = 0; p2 = 1; p3 = 0; p4 = 1;
  #1 p1 = 0; p2 = 1; p3 = 1; p4 = 0;
  #1 p1 = 0; p2 = 1; p3 = 1; p4 = 1;
  #1 p1 = 1; p2 = 0; p3 = 0; p4 = 0;
  #1 p1 = 1; p2 = 0; p3 = 0; p4 = 1;
  #1 p1 = 1; p2 = 0; p3 = 1; p4 = 0;
  #1 p1 = 1; p2 = 0; p3 = 1; p4 = 1;
  #1 p1 = 1; p2 = 1; p3 = 0; p4 = 0;
  #1 p1 = 1; p2 = 1; p3 = 0; p4 = 1;
  #1 p1 = 1; p2 = 1; p3 = 1; p4 = 0;
  #1 p1 = 1; p2 = 1; p3 = 1; p4 = 1;
end // Termina en tiempo 15

initial begin // Display de la tabla de verdad modulo 2
   #16
   $display("\n");
   $display("A B C | Y");
   $display("------|--");
   $monitor("%b %b %b | %b", p5, p6, p7, out2);
     p5 = 0; p6 = 0; p7 = 0;
  #1 p5 = 0; p6 = 0; p7 = 1;
  #1 p5 = 0; p6 = 1; p7 = 0;
  #1 p5 = 0; p6 = 1; p7 = 1;
  #1 p5 = 1; p6 = 0; p7 = 0;
  #1 p5 = 1; p6 = 0; p7 = 1;
  #1 p5 = 1; p6 = 1; p7 = 0;
  #1 p5 = 1; p6 = 1; p7 = 1;
end // Termina en tiempo 23

initial begin// Display de la tabla de verdad modulo 3
   #24
   $display("\n");
   $display("A B C | Y");
   $display("------|--");
   $monitor("%b %b %b | %b", p8, p9, p10, out3);
     p8 = 0; p9 = 0; p10 = 0;
  #1 p8 = 0; p9 = 0; p10 = 1;
  #1 p8 = 0; p9 = 1; p10 = 0;
  #1 p8 = 0; p9 = 1; p10 = 1;
  #1 p8 = 1; p9 = 0; p10 = 0;
  #1 p8 = 1; p9 = 0; p10 = 1;
  #1 p8 = 1; p9 = 1; p10 = 0;
  #1 p8 = 1; p9 = 1; p10 = 1;
end // Termina en tiempo 32

initial begin// Display de la tabla de verdad modulo 4
   #32
   $display("\n");
   $display("A B C | Y");
   $display("------|--");
   $monitor("%b %b %b | %b", p11, p12, p13, out4);
     p11 = 0; p12 = 0; p13 = 0;
  #1 p11 = 0; p12 = 0; p13 = 1;
  #1 p11 = 0; p12 = 1; p13 = 0;
  #1 p11 = 0; p12 = 1; p13 = 1;
  #1 p11 = 1; p12 = 0; p13 = 0;
  #1 p11 = 1; p12 = 0; p13 = 1;
  #1 p11 = 1; p12 = 1; p13 = 0;
  #1 p11 = 1; p12 = 1; p13 = 1;
end // Termina en tiempo 39

// Iniciar la funcion del GtkWave

initial 
    #40 $finish;

initial begin
  $dumpfile("GatesLevel_tb.vcd");
  $dumpvars(0, testbench);
end

endmodule

Lab_04/Gate_level/GatesLevel_tb.vcd
$date
	Fri Aug 07 02:33:06 2020
$end
$version
	Icarus Verilog
$end
$timescale
	1ps
$end
$scope module testbench $end
$var wire 1 ! out4 $end
$var wire 1 " out3 $end
$var wire 1 # out2 $end
$var wire 1 $ out1 $end
$var reg 1 % p1 $end
$var reg 1 & p10 $end
$var reg 1 ' p11 $end
$var reg 1 ( p12 $end
$var reg 1 ) p13 $end
$var reg 1 * p2 $end
$var reg 1 + p3 $end
$var reg 1 , p4 $end
$var reg 1 - p5 $end
$var reg 1 . p6 $end
$var reg 1 / p7 $end
$var reg 1 0 p8 $end
$var reg 1 1 p9 $end
$scope module G1 $end
$var wire 1 2 A1 $end
$var wire 1 3 A2 $end
$var wire 1 4 A3 $end
$var wire 1 5 A4 $end
$var wire 1 6 A5 $end
$var wire 1 7 A6 $end
$var wire 1 8 A7 $end
$var wire 1 9 A8 $end
$var wire 1 : N1 $end
$var wire 1 ; N2 $end
$var wire 1 < N3 $end
$var wire 1 = N4 $end
$var wire 1 $ Y $end
$var wire 1 % inA $end
$var wire 1 * inB $end
$var wire 1 + inC $end
$var wire 1 , inD $end
$upscope $end
$scope module G2 $end
$var wire 1 > N1 $end
$var wire 1 # Y $end
$var wire 1 - inA $end
$var wire 1 . inB $end
$var wire 1 / inC $end
$upscope $end
$scope module G3 $end
$var wire 1 ? A1 $end
$var wire 1 @ A2 $end
$var wire 1 A N2 $end
$var wire 1 " Y $end
$var wire 1 0 inA $end
$var wire 1 1 inB $end
$var wire 1 & inC $end
$upscope $end
$scope module G4 $end
$var wire 1 B A1 $end
$var wire 1 C A2 $end
$var wire 1 D N1 $end
$var wire 1 E N3 $end
$var wire 1 ! Y $end
$var wire 1 ' inA $end
$var wire 1 ( inB $end
$var wire 1 ) inC $end
$upscope $end
$upscope $end
$enddefinitions $end
#0
$dumpvars
xE
xD
xC
xB
xA
x@
x?
x>
1=
1<
1;
1:
09
08
07
06
05
04
03
12
x1
x0
x/
x.
x-
0,
0+
0*
x)
x(
x'
x&
0%
1$
x#
x"
x!
$end
#1
0$
02
0=
1,
#2
1=
0<
0,
1+
#3
1$
0=
13
1,
#4
0$
1=
1<
03
0;
0,
0+
1*
#5
1$
0=
14
1,
#6
1$
15
1=
04
0<
0,
1+
#7
0$
05
0=
1,
#8
1=
1<
1;
0:
0,
0+
0*
1%
#9
1$
0=
18
1,
#10
1$
19
1=
08
0<
0,
1+
#11
0$
09
0=
1,
#12
1$
16
1=
1<
0;
0,
0+
1*
#13
0$
06
0=
1,
#14
1=
0<
0,
1+
#15
1$
0=
17
1,
#16
1#
1>
0/
0.
0-
#17
1/
#18
0#
0>
0/
1.
#19
1/
#20
1#
1>
0/
0.
1-
#21
1/
#22
0#
0>
0/
1.
#23
1/
#24
1"
1?
1A
0@
0&
01
00
#25
1&
#26
0"
0?
0A
0&
11
#27
1"
1@
1&
#28
1?
1"
1A
0@
0&
01
10
#29
1&
#30
0"
0?
0A
0&
11
#31
1"
1@
1&
#32
1!
1B
1E
0C
1D
0)
0(
0'
#33
0!
0B
0E
1)
#34
1B
1!
1E
1C
0)
1(
#35
0B
0E
1)
#36
0!
1E
0C
0D
0)
0(
1'
#37
0E
1)
#38
1!
1E
1C
0)
1(
#39
0E
1)
