Lab_09/Ejercicio05/ROM.v
//Electronica Digital 1
// Marco Duarte
// Ejercicio 04
// Buffer Tri-Estado

module ROML(
    input wire En,
    input wire [6:0]in,
    output reg [12:0]out);

        always @ (En or in)begin
                out = 0;
            if ( En )
                casex (in)
                    7'bxxxxxx0: out <= 13'b1000000001000;
                    7'b00001x1: out <= 13'b0100000001000;
                    7'b00000x1: out <= 13'b1000000001000;
                    7'b00011x1: out <= 13'b1000000001000;
                    7'b00010x1: out <= 13'b1000000001000;
                    7'b0010xx1: out <= 13'b1000000001000;
                    7'b0011xx1: out <= 13'b1000000001000;
                    7'b0100xx1: out <= 13'b0011010000010;
                    7'b0101xx1: out <= 13'b0011010000100;
                    7'b0110xx1: out <= 13'b1011010100000;
                    7'b0111xx1: out <= 13'b1000000111000;
                    7'b1000x11: out <= 13'b0100000001000;
                    7'b1000x01: out <= 13'b1000000001000;
                    7'b1001x11: out <= 13'b1000000001000;
                    7'b1001x01: out <= 13'b0100000001000;
                    7'b1010xx1: out <= 13'b0011011000010;
                    7'b1011xx1: out <= 13'b1011011100000;
                    7'b1100xx1: out <= 13'b0100000001000;
                    7'b1101xx1: out <= 13'b0000000001001;
                    7'b1110xx1: out <= 13'b0011100000010;
                    7'b1111xx1: out <= 13'b1011100100000;
                endcase
        end
endmodule

Lab_09/Ejercicio05/ROM_tb.v
// Marco Duarte
// TestBench
// Ejercicio 05

module testbench();

reg En;
reg [6:0]in;
wire [12:0]out;

ROML U01(En, in, out);

initial begin
    #1
    $display("-----------------");
    $display("| Enable | Input | Output |");
    $monitor("|   %b    |   %b  |   %b   |", En, in, out);
    En = 0; in = 7'b0101010;
    #2 En = 1; in = 7'b0101010;
    #2 in = 7'b0000101;
    #2 in = 7'bxxxxxx0;
    #2 in = 7'b00001x1;
    #2 in = 7'b00000x1;
    #2 in = 7'b00011x1;
    #2 in = 7'b00010x1;
    #2 in = 7'b0010xx1;
    #2 in = 7'b0011xx1;
    #2 in = 7'b0100xx1;
    #2 in = 7'b0101xx1;
    #2 in = 7'b0110xx1;
    #2 in = 7'b0111xx1;
    #2 in = 7'b1000x11;
    #2 in = 7'b1000x01;
    #2 in = 7'b1001x11;
    #2 in = 7'b1001x01;
    #2 in = 7'b1010xx1;
    #2 in = 7'b1011xx1;
    #2 in = 7'b1100xx1;
    #2 in = 7'b1101xx1;
    #2 in = 7'b1110xx1;
    #2 En = 0; in = 7'b1110xx1;
    #2 En = 1; in = 7'b1101011;
    #2 in = 7'b11x1x01;
    #2 in = 7'b1xx1xx1;
    #2 in = 7'b1x10xx1;
    #2 in = 7'b10x10x1;
    #2 in = 7'bxx10xx1;
    #2 in = 7'b0000xx1;
    #2 in = 7'bxxxx1xx;
    #2 in = 7'b0110xx1;
    #2 in = 7'b0010xx1;

end

initial
    #100 $finish;

initial begin
    $dumpfile("ROM_tb.vcd");
    $dumpvars(0, testbench); 
end

endmodule

Lab_09/Ejercicio05/ROM_tb.vcd
$date
	Fri Oct 30 22:42:51 2020
$end
$version
	Icarus Verilog
$end
$timescale
	1ps
$end
$scope module testbench $end
$var wire 13 ! out [12:0] $end
$var reg 1 " En $end
$var reg 7 # in [6:0] $end
$scope module U01 $end
$var wire 1 " En $end
$var wire 7 $ in [6:0] $end
$var reg 13 % out [12:0] $end
$upscope $end
$upscope $end
$enddefinitions $end
#0
$dumpvars
bx %
bx $
bx #
x"
bx !
$end
#1
b0 !
b0 %
b101010 #
b101010 $
0"
#3
b1000000001000 !
b1000000001000 %
1"
#5
b100000001000 !
b100000001000 %
b101 #
b101 $
#7
b1000000001000 !
b1000000001000 %
bx0 #
bx0 $
#9
b100000001000 !
b100000001000 %
b1x1 #
b1x1 $
#11
b1000000001000 !
b1000000001000 %
b0x1 #
b0x1 $
#13
b1000000001000 !
b1000000001000 %
b11x1 #
b11x1 $
#15
b1000000001000 !
b1000000001000 %
b10x1 #
b10x1 $
#17
b1000000001000 !
b1000000001000 %
b10xx1 #
b10xx1 $
#19
b1000000001000 !
b1000000001000 %
b11xx1 #
b11xx1 $
#21
b11010000010 !
b11010000010 %
b100xx1 #
b100xx1 $
#23
b11010000100 !
b11010000100 %
b101xx1 #
b101xx1 $
#25
b1011010100000 !
b1011010100000 %
b110xx1 #
b110xx1 $
#27
b1000000111000 !
b1000000111000 %
b111xx1 #
b111xx1 $
#29
b100000001000 !
b100000001000 %
b1000x11 #
b1000x11 $
#31
b1000000001000 !
b1000000001000 %
b1000x01 #
b1000x01 $
#33
b1000000001000 !
b1000000001000 %
b1001x11 #
b1001x11 $
#35
b100000001000 !
b100000001000 %
b1001x01 #
b1001x01 $
#37
b11011000010 !
b11011000010 %
b1010xx1 #
b1010xx1 $
#39
b1011011100000 !
b1011011100000 %
b1011xx1 #
b1011xx1 $
#41
b100000001000 !
b100000001000 %
b1100xx1 #
b1100xx1 $
#43
b1001 !
b1001 %
b1101xx1 #
b1101xx1 $
#45
b11100000010 !
b11100000010 %
b1110xx1 #
b1110xx1 $
#47
b0 !
b0 %
0"
#49
b1001 !
b1001 %
b1101011 #
b1101011 $
1"
#51
b1001 !
b1001 %
b11x1x01 #
b11x1x01 $
#53
b1000000001000 !
b1000000001000 %
b1xx1xx1 #
b1xx1xx1 $
#55
b11011000010 !
b11011000010 %
b1x10xx1 #
b1x10xx1 $
#57
b1000000001000 !
b1000000001000 %
b10x10x1 #
b10x10x1 $
#59
b1000000001000 !
b1000000001000 %
bx10xx1 #
bx10xx1 $
#61
b100000001000 !
b100000001000 %
b0xx1 #
b0xx1 $
#63
b1000000001000 !
b1000000001000 %
bx1xx #
bx1xx $
#65
b1011010100000 !
b1011010100000 %
b110xx1 #
b110xx1 $
#67
b1000000001000 !
b1000000001000 %
b10xx1 #
b10xx1 $
