Lab_09/Ejercicio03/FlipFlopJK.v
    //Electronica Digital 1
    // Marco Duarte
    // Ejercicio 03
    // FlipFlop tipo JK

module FFD(
    input wire clk, reset, En, D,
    output reg Q);

        always @(posedge clk or posedge reset) begin
            if(reset)
                Q <= 0;
            else if (En)
                Q <= D; 
        end
endmodule

module FFJK(
    input wire clk, reset, En, J, K,
    output wire Q);

        wire nQ, nK, aJ, aK, q;

        not(nQ, Q);
        not(nK, K);
        and(aJ, J, nQ);
        and(aK, nK, Q);
        or(q, aJ, aK);

        FFD U1(clk, reset, En, q, Q);
endmodule

Lab_09/Ejercicio03/FlipFlopJK_tb.v
// Marco Duarte
// TestBench
// Ejercicio 03

module testbench();

reg clk, reset, En, J, K;
wire Q;

FFJK FlipFlopJK(clk, reset, En, J, K, Q);

initial begin
    #1
    $display("----------------------------------");
    $display("| Clock | Reset | En | J | K | Q |");
    $monitor("|   %b   |   %b   |  %b | %b | %b | %b |", clk, reset, En, J, K, Q);
    clk = 0; reset = 0; En = 0; J = 0; K = 0;
    #2 reset = 0;
    #2 reset = 1;
    #2 reset = 0;
    #2 En = 1; J = 1;
    #2 En = 0;
    #2 En = 1; J = 0;
    #2 K = 1;
    #2 J = 1; K = 0;
    #2 K = 1;
end

always
    #1 clk = ~clk;

initial
    #25 $finish;

initial begin
    $dumpfile("FlipFlopJK_tb.vcd");
    $dumpvars(0, testbench);   
end

endmodule

Lab_09/Ejercicio03/FlipFlopJK_tb.vcd
$date
	Fri Oct 30 18:32:10 2020
$end
$version
	Icarus Verilog
$end
$timescale
	1ps
$end
$scope module testbench $end
$var wire 1 ! Q $end
$var reg 1 " En $end
$var reg 1 # J $end
$var reg 1 $ K $end
$var reg 1 % clk $end
$var reg 1 & reset $end
$scope module FlipFlopJK $end
$var wire 1 " En $end
$var wire 1 # J $end
$var wire 1 $ K $end
$var wire 1 ' aJ $end
$var wire 1 ( aK $end
$var wire 1 % clk $end
$var wire 1 ) nK $end
$var wire 1 * nQ $end
$var wire 1 + q $end
$var wire 1 & reset $end
$var wire 1 ! Q $end
$scope module U1 $end
$var wire 1 + D $end
$var wire 1 " En $end
$var wire 1 % clk $end
$var wire 1 & reset $end
$var reg 1 ! Q $end
$upscope $end
$upscope $end
$upscope $end
$enddefinitions $end
#0
$dumpvars
x+
x*
x)
x(
x'
x&
x%
x$
x#
x"
x!
$end
#1
1)
0'
0$
0#
0"
0&
1%
#2
0%
#3
1%
#4
0%
#5
0+
0(
1*
0!
1%
1&
#6
0%
#7
1%
0&
#8
0%
#9
1+
1'
1%
1#
1"
#10
0%
#11
1%
0"
#12
0%
#13
1(
0*
1!
1+
0'
1%
0#
1"
#14
0%
#15
0+
0(
0)
1%
1$
#16
0%
#17
1'
1*
0!
1+
0(
1)
1%
0$
1#
#18
0%
#19
0+
0'
0*
1!
0)
1%
1$
#20
0%
#21
1+
1'
1*
0!
1%
#22
0%
#23
0+
0'
0*
1!
1%
#24
0%
#25
1+
1'
1*
0!
1%
