Lab_09/Ejercicio01/FlipFlop.v
// Electronica Digital 1
// Marco Duarte
// Ejercicio 01
// FlipFlop

module FFD_1(
    input wire clk, reset, En, D, 
    output reg Q);

    always @ (posedge clk or posedge reset) begin
        if (reset) 
            Q <= 1'b0;
        else if (En)
            Q <= D;
    end
endmodule

module FFD_2(
    input wire clk, reset, En, 
    input wire [1:0]D2, 
    output wire [1:0]Q2);

    FFD_1 U1(clk, reset, En, D2[1], Q2[1]);
    FFD_1 U2(clk, reset, En, D2[0], Q2[0]);

endmodule

module FFD_4(
    input wire clk, reset, En,
    input wire [3:0]D4, 
    output wire [3:0]Q4);

    FFD_2 U1(clk, reset, En, D4[1:0], Q4[1:0]);
    FFD_2 U2(clk, reset, En, D4[3:2], Q4[3:2]);

endmodule

Lab_09/Ejercicio01/FlipFlop_tb.v
// Marco DUarte
// TestBench
// Ejercicio 01

module testbench();

reg clk, reset, En, D;
reg [1:0]D2;
reg [3:0]D4;
wire Q;
wire [1:0]Q2;
wire [3:0]Q4;

FFD_1 FF01(clk, reset, En, D, Q);
FFD_2 FF02(clk, reset, En, D2, Q2);
FFD_4 FF03(clk, reset, En, D4, Q4);


initial begin
    #1
    $display("--------------------------");
    $display("| Clock | Reset | En | D   D2   D4   | Q  Q2  Q4 |");
    $monitor("|   %b  |   %b   |  %b  | %b  %b   %b  | %b  %b  %b  |", clk, reset, En, D, D2, D4, Q, Q2, Q4);
    clk = 0; reset = 0; En = 0; D = 0; D2 = 2'b00; D4 = 4'b0000; 
    #2 reset = 1;
    #2 reset = 0;
    #2 En = 1;
    #2 D = 1; D2 = 2'b01; D4 = 4'b0001;
    #2 D2 = 2'b10; D4 = 4'b0011;
    #2 D2 = 2'b11; D4 = 4'b1100;
    #2 D = 0;
  end
  
   always
    #1  clk = ~clk;
  
  initial 
  #20 $finish;

  initial begin
      $dumpfile("FlipFlop_tb.vcd");
      $dumpvars(0, testbench);
    
  end

endmodule

Lab_09/Ejercicio01/FlipFlop.vcd
$date
	Thu Oct 29 20:58:57 2020
$end
$version
	Icarus Verilog
$end
$timescale
	1ps
$end
$scope module testbench $end
$var wire 4 ! Q4 [3:0] $end
$var wire 2 " Q2 [1:0] $end
$var wire 1 # Q $end
$var reg 1 $ D $end
$var reg 2 % D2 [1:0] $end
$var reg 4 & D4 [3:0] $end
$var reg 1 ' En $end
$var reg 1 ( clk $end
$var reg 1 ) reset $end
$scope module FF01 $end
$var wire 1 $ D $end
$var wire 1 ' En $end
$var wire 1 ( clk $end
$var wire 1 ) reset $end
$var reg 1 # Q $end
$upscope $end
$scope module FF02 $end
$var wire 2 * D2 [1:0] $end
$var wire 1 ' En $end
$var wire 1 ( clk $end
$var wire 1 ) reset $end
$var wire 2 + Q2 [1:0] $end
$scope module U1 $end
$var wire 1 , D $end
$var wire 1 ' En $end
$var wire 1 ( clk $end
$var wire 1 ) reset $end
$var reg 1 - Q $end
$upscope $end
$scope module U2 $end
$var wire 1 . D $end
$var wire 1 ' En $end
$var wire 1 ( clk $end
$var wire 1 ) reset $end
$var reg 1 / Q $end
$upscope $end
$upscope $end
$scope module FF03 $end
$var wire 4 0 D4 [3:0] $end
$var wire 1 ' En $end
$var wire 1 ( clk $end
$var wire 1 ) reset $end
$var wire 4 1 Q4 [3:0] $end
$scope module U1 $end
$var wire 2 2 D2 [1:0] $end
$var wire 1 ' En $end
$var wire 1 ( clk $end
$var wire 1 ) reset $end
$var wire 2 3 Q2 [1:0] $end
$scope module U1 $end
$var wire 1 4 D $end
$var wire 1 ' En $end
$var wire 1 ( clk $end
$var wire 1 ) reset $end
$var reg 1 5 Q $end
$upscope $end
$scope module U2 $end
$var wire 1 6 D $end
$var wire 1 ' En $end
$var wire 1 ( clk $end
$var wire 1 ) reset $end
$var reg 1 7 Q $end
$upscope $end
$upscope $end
$scope module U2 $end
$var wire 2 8 D2 [1:0] $end
$var wire 1 ' En $end
$var wire 1 ( clk $end
$var wire 1 ) reset $end
$var wire 2 9 Q2 [1:0] $end
$scope module U1 $end
$var wire 1 : D $end
$var wire 1 ' En $end
$var wire 1 ( clk $end
$var wire 1 ) reset $end
$var reg 1 ; Q $end
$upscope $end
$scope module U2 $end
$var wire 1 < D $end
$var wire 1 ' En $end
$var wire 1 ( clk $end
$var wire 1 ) reset $end
$var reg 1 = Q $end
$upscope $end
$upscope $end
$upscope $end
$upscope $end
$enddefinitions $end
#0
$dumpvars
x=
x<
x;
x:
bx 9
bx 8
x7
x6
x5
x4
bx 3
bx 2
bx 1
bx 0
x/
x.
x-
x,
bx +
bx *
x)
x(
x'
bx &
bx %
x$
x#
bx "
bx !
$end
#1
04
06
0:
0<
b0 2
b0 8
0,
0.
b0 &
b0 0
b0 %
b0 *
0$
0'
0)
1(
#2
0(
#3
0=
b0 9
0;
07
b0 !
b0 1
b0 3
05
0/
b0 "
b0 +
0-
0#
1(
1)
#4
0(
#5
1(
0)
#6
0(
#7
1(
1'
#8
0(
#9
1#
b1 "
b1 +
1/
16
b1 2
1.
1(
b1 &
b1 0
b1 %
b1 *
1$
#10
0(
#11
b1 !
b1 1
b1 3
17
0/
b10 "
b10 +
1-
14
b11 2
1,
0.
1(
b11 &
b11 0
b10 %
b10 *
#12
0(
#13
b11 "
b11 +
1/
b11 !
b11 1
b11 3
15
04
06
1:
1<
b0 2
b11 8
1.
1(
b1100 &
b1100 0
b11 %
b11 *
#14
0(
#15
1=
b11 9
1;
07
b1100 !
b1100 1
b0 3
05
0#
1(
0$
