Lab_08/ALU/ALU.v
// Electronica Digital 1
// Marco Duarte - 19022
// Laboratorio 8
// ALU
//----------------------------

module ALU(
    input wire [3:0]A, // Los bits para seleccionar en A
    input wire [3:0]B, // Los bits para seleccionar en B
    input wire [2:0]command, // Aca es donde le damos la instruccion a la ALU
    output reg [3:0]result); // El resultado de la operacion que se haga


        always @ (A or B or command) begin

            // El case sirve para asignarle un valor a cada opcion
            case(command)
                3'b000: result = A & B; // Opcion de AND
                3'b001: result = A | B; // Opcion de OR
                3'b010: result = A + B; // Opcion de sumar
                3'b100: result = A & ~B; // Opcion de AND y B negado
                3'b101: result = A | ~B; // Opcion de OR y B negado
                3'b110: result = A - B; // Opcion de resta
                3'b111: result = (A < B) ? 1:0; // Opcion de comparacion si es A mayor que B 0000
                default: result = 4'b0000; // Si no esta la opcion se asigna 0000
            endcase
        end
endmodule

Lab_08/ALU/ALU_tb.v
// Electronica Digital 1
// Marco DUarte 
// Testbench
//---------------------------

module testbench();

reg [3:0]A;
reg [3:0]B;
reg [2:0]command;
wire [3:0]result;

ALU test(A, B, command, result);

initial begin
    #1
    $display("--------------------------------------------");
    $display("|   A    |   B     |   C    |   Result     |");
    $monitor("|  %b  |  %b   |  %b   |     %b     |", A, B, command, result);
        A = 4'b0000; B = 4'b0000; command = 3'b000;
    #1 A = 4'b0001; B = 4'b0001; command = 3'b000;
    #1 A = 4'b0001; B = 4'b0000; command = 3'b000;
    #1 A = 4'b0100; B = 4'b0110; command = 3'b000;
    #1 A = 4'b0001; B = 4'b0001; command = 3'b001;
    #1 A = 4'b0001; B = 4'b0000; command = 3'b001;
    #1 A = 4'b0000; B = 4'b0000; command = 3'b001;
    #1 A = 4'b0001; B = 4'b0001; command = 3'b010;
    #1 A = 4'b0010; B = 4'b0010; command = 3'b010;
    #1 A = 4'b0001; B = 4'b0001; command = 3'b010;
    #1 A = 4'b0001; B = 4'b0001; command = 3'b100;
    #1 A = 4'b0001; B = 4'b0000; command = 3'b100;
    #1 A = 4'b0001; B = 4'b0001; command = 3'b101;
    #1 A = 4'b0001; B = 4'b0000; command = 3'b101;
    #1 A = 4'b0001; B = 4'b0001; command = 3'b110;
    #1 A = 4'b1000; B = 4'b0001; command = 3'b110;
    #1 A = 4'b1000; B = 4'b1000; command = 3'b111;
    #1 A = 4'b0000; B = 4'b0001; command = 3'b111;
    #1 A = 4'b0001; B = 4'b0001; command = 3'b011;
end

initial 
    #21 $finish;

initial begin
   $dumpfile("ALU_tb.vcd");
   $dumpvars(0, testbench); 
end

endmodule

Lab_08/ALU/ALU_tb.vcd
$date
	Sat Oct 24 21:19:27 2020
$end
$version
	Icarus Verilog
$end
$timescale
	1ps
$end
$scope module testbench $end
$var wire 4 ! result [3:0] $end
$var reg 4 " A [3:0] $end
$var reg 4 # B [3:0] $end
$var reg 3 $ command [2:0] $end
$scope module test $end
$var wire 4 % A [3:0] $end
$var wire 4 & B [3:0] $end
$var wire 3 ' command [2:0] $end
$var reg 4 ( result [3:0] $end
$upscope $end
$upscope $end
$enddefinitions $end
#0
$dumpvars
bx (
bx '
bx &
bx %
bx $
bx #
bx "
bx !
$end
#1
b0 !
b0 (
b0 $
b0 '
b0 #
b0 &
b0 "
b0 %
#2
b1 !
b1 (
b1 #
b1 &
b1 "
b1 %
#3
b0 !
b0 (
b0 #
b0 &
#4
b100 !
b100 (
b110 #
b110 &
b100 "
b100 %
#5
b1 !
b1 (
b1 $
b1 '
b1 #
b1 &
b1 "
b1 %
#6
b0 #
b0 &
#7
b0 !
b0 (
b0 "
b0 %
#8
b10 !
b10 (
b10 $
b10 '
b1 #
b1 &
b1 "
b1 %
#9
b100 !
b100 (
b10 #
b10 &
b10 "
b10 %
#10
b10 !
b10 (
b1 #
b1 &
b1 "
b1 %
#11
b0 !
b0 (
b100 $
b100 '
#12
b1 !
b1 (
b0 #
b0 &
#13
b1111 !
b1111 (
b101 $
b101 '
b1 #
b1 &
#14
b0 #
b0 &
#15
b0 !
b0 (
b110 $
b110 '
b1 #
b1 &
#16
b111 !
b111 (
b1000 "
b1000 %
#17
b0 !
b0 (
b111 $
b111 '
b1000 #
b1000 &
#18
b1 !
b1 (
b1 #
b1 &
b0 "
b0 %
#19
b0 !
b0 (
b11 $
b11 '
b1 "
b1 %
