01_Tabla_SOP/SOP#01.v
// Marco Duarte - 19022
// SOP tabla_01

module Lab_03();

// Declaracion de variables por modulo del circuito

wire N1, N2, N3; // Not del circuito
wire O1; // Or del circutio
wire A1, A2, A3, A4, A5; // And del circuito

reg inA, inB, inC; // Declarando que el circuito tiene 3 entradas

//Declaracion de compuertas

not NA (N1,   inA); // A not
not NB (N2,   inB); // B not
not NC (N3,   inC); // C not
and AA (A1,   N1, N2, N3); // Las 3 entradas del And_1
and AB (A2,   N1, inB, N3); // Las 3 entradas del And_2
and AC (A3,   inA, N2, N3); // Las 3 entradas del And_3
and AD (A4,   inA, N2, inC); // Las 3 entradas del And_4
and AE (A5,   inA, inB, inC); // Las 3 entradas del And_5
or OA (O1,    A1, A2, A3, A4, A5); //Las 3 entradas del Or

initial // Inicio el codigo luego de establecer las condiciones
  begin
    $display("A B C| Y");
    $display("-------");
    $monitor("%b %b %b | %b", inA, inB, inC, O1);

// Inputs en 0
inA = 0;
inB = 0;
inC = 0;

// Declaramos los cambios en los tiempos
#1 inC = 1; // #1 marca un retardo de una unidad de tiempo
#1 inB = 1; inC = 0;
#1 inC = 1;
#1 inA = 1; inB = 0; inC = 0;
#1 inC = 1;
#1 inB = 1; inC = 0;
#1 inC = 1;
#1 $finish; // termina la simulacion
end

initial
  begin
    $dumpfile("SOP#01_tb.vcd");
    $dumpvars(0, Lab_03);
  end
endmodule //finalizar el modulo

01_Tabla_SOP/SOP#01_tb.vcd
$date
	Fri Jul 31 02:20:32 2020
$end
$version
	Icarus Verilog
$end
$timescale
	1ps
$end
$scope module Lab_03 $end
$var wire 1 ! A1 $end
$var wire 1 " A2 $end
$var wire 1 # A3 $end
$var wire 1 $ A4 $end
$var wire 1 % A5 $end
$var wire 1 & N1 $end
$var wire 1 ' N2 $end
$var wire 1 ( N3 $end
$var wire 1 ) O1 $end
$var reg 1 * inA $end
$var reg 1 + inB $end
$var reg 1 , inC $end
$upscope $end
$enddefinitions $end
#0
$dumpvars
0,
0+
0*
1)
1(
1'
1&
0%
0$
0#
0"
1!
$end
#1
0)
0!
0(
1,
#2
1)
1"
1(
0'
0,
1+
#3
0)
0"
0(
1,
#4
1)
1#
1(
1'
0&
0,
0+
1*
#5
0#
1$
0(
1,
#6
0)
0$
1(
0'
0,
1+
#7
1)
1%
0(
1,
